dls_powerpmacanalyse/__init__.py
dls_powerpmacanalyse/_version_git.py
dls_powerpmacanalyse/dls_ppmacanalyse.py
dls_powerpmacanalyse/htmlDisp.py
dls_powerpmacanalyse/login.py
dls_powerpmacanalyse/ppmacanalyse_control.py
dls_powerpmacanalyse/ui_formAnalyseControl.py
dls_powerpmacanalyse/ui_formLogin.py
dls_powerpmacanalyse-3.0.0b1.dist-info/LICENSE
dls_powerpmacanalyse-3.0.0b1.dist-info/METADATA
dls_powerpmacanalyse-3.0.0b1.dist-info/WHEEL
dls_powerpmacanalyse-3.0.0b1.dist-info/entry_points.txt
dls_powerpmacanalyse-3.0.0b1.dist-info/top_level.txt
dls_powerpmacanalyse-3.0.0b1.dist-info/RECORD
